ol_concourse/__init__.py
ol_concourse/lib/__init__.py
ol_concourse/lib/constants.py
ol_concourse/lib/containers.py
ol_concourse/lib/notifications.py
ol_concourse/lib/resource_types.py
ol_concourse/lib/resources.py
ol_concourse/lib/tasks.py
ol_concourse/lib/jobs/__init__.py
ol_concourse/lib/jobs/infrastructure.py
ol_concourse/lib/models/__init__.py
ol_concourse/lib/models/fragment.py
ol_concourse/lib/models/pipeline.py
ol_concourse/lib/models/resource.py
ol_concourse-0.5.8.dist-info/METADATA
ol_concourse-0.5.8.dist-info/WHEEL
ol_concourse-0.5.8.dist-info/namespace_packages.txt
ol_concourse-0.5.8.dist-info/top_level.txt
ol_concourse-0.5.8.dist-info/RECORD
