Metadata-Version: 2.1
Name: ol-concourse
Version: 0.5.8
Requires-Python: >=3.12
Requires-Dist: pydantic<3.0.0,>=2
